olvid/__init__.py
olvid/__main__.py
olvid/version.py
olvid/cli/__init__.py
olvid/cli/interactive_main.py
olvid/cli/interactive_tree.py
olvid/cli/listen.py
olvid/cli/root_tree.py
olvid/cli/handler/__init__.py
olvid/cli/handler/attachment_tree.py
olvid/cli/handler/contact_tree.py
olvid/cli/handler/discussion_tree.py
olvid/cli/handler/group_tree.py
olvid/cli/handler/identity_tree.py
olvid/cli/handler/invitation_tree.py
olvid/cli/handler/key_tree.py
olvid/cli/handler/message_tree.py
olvid/cli/handler/storage_tree.py
olvid/cli/handler/tools_tree.py
olvid/cli/tools/ClientSingleton.py
olvid/cli/tools/__init__.py
olvid/cli/tools/auto_invitation.py
olvid/cli/tools/cli_tools.py
olvid/cli/tools/click_wrappers.py
olvid/cli/tools/exceptions.py
olvid/cli/tools/interactive_actions.py
olvid/core/OlvidAdminClient.py
olvid/core/OlvidBot.py
olvid/core/OlvidClient.py
olvid/core/StubHolder.py
olvid/core/__init__.py
olvid/core/logger.py
olvid/datatypes/__init__.py
olvid/datatypes/datatypes.py
olvid/internal/__init__.py
olvid/internal/admin/__init__.py
olvid/internal/admin/admin.py
olvid/internal/commands/__init__.py
olvid/internal/commands/commands.py
olvid/internal/notifications/__init__.py
olvid/internal/notifications/notifications.py
olvid/internal/types/__init__.py
olvid/internal/types/types.py
olvid/listeners/ClientListenerHolder.py
olvid/listeners/Command.py
olvid/listeners/GenericNotificationListener.py
olvid/listeners/ListenersImplementation.py
olvid/listeners/Notifications.py
olvid/listeners/__init__.py
olvid/protobuf/__init__.py
olvid/protobuf/olvid/daemon/admin/v1/client_key_admin_pb2.py
olvid/protobuf/olvid/daemon/admin/v1/client_key_admin_pb2_grpc.py
olvid/protobuf/olvid/daemon/admin/v1/identity_admin_pb2.py
olvid/protobuf/olvid/daemon/admin/v1/identity_admin_pb2_grpc.py
olvid/protobuf/olvid/daemon/command/v1/attachment_commands_pb2.py
olvid/protobuf/olvid/daemon/command/v1/attachment_commands_pb2_grpc.py
olvid/protobuf/olvid/daemon/command/v1/contact_commands_pb2.py
olvid_bot-1.0.0.post2.dist-info/LICENSE
olvid_bot-1.0.0.post2.dist-info/METADATA
olvid_bot-1.0.0.post2.dist-info/WHEEL
olvid_bot-1.0.0.post2.dist-info/entry_points.txt
olvid_bot-1.0.0.post2.dist-info/top_level.txt
olvid_bot-1.0.0.post2.dist-info/RECORD
