Metadata-Version: 2.1
Name: olvid-bot
Version: 1.0.0.post2
Summary: An high-level module to create bots in Olvid application
Author: olvid.io
Author-email: Olvid <bot@olvid.io>
Maintainer-email: Olvid <bot@olvid.io>
License: GNU AFFERO GENERAL PUBLIC LICENSE
Project-URL: GitHug, https://github.com/olvid-io/Olvid-Bot-Python-Client
Project-URL: Issues, https://github.com/olvid-io/Olvid-Bot-Python-Client/issues
Project-URL: Quickstart, https://github.com/olvid-io/Olvid-Bot-Quickstart
Project-URL: Website, https://olvid.io
Keywords: olvid,daemon,bot
Classifier: Development Status :: 4 - Beta
Classifier: Intended Audience :: Developers
Classifier: Topic :: Software Development
Classifier: Operating System :: OS Independent
Requires-Python: >=3.10
License-File: LICENSE
Requires-Dist: grpcio ==1.65.4
Requires-Dist: grpcio-tools ==1.65.4
Requires-Dist: protobuf ==5.27.3
Requires-Dist: asyncclick ==8.1.7.2
Requires-Dist: anyio ==4.4.0
Requires-Dist: uvloop ==0.19.0
